spell/__init__.py
spell/constants.py
spell/deployment_constants.py
spell/metrics.py
spell/version.py
spell/api/__init__.py
spell/api/admin_client.py
spell/api/base_client.py
spell/api/client.py
spell/api/cluster_client.py
spell/api/config_client.py
spell/api/exceptions.py
spell/api/features_client.py
spell/api/feedback_client.py
spell/api/hyper_client.py
spell/api/jupyter_workspaces_client.py
spell/api/keys_client.py
spell/api/links_client.py
spell/api/model_client.py
spell/api/model_server_client.py
spell/api/models.py
spell/api/projects_client.py
spell/api/resources_client.py
spell/api/runs_client.py
spell/api/supported_options_client.py
spell/api/user_client.py
spell/api/user_datasets_client.py
spell/api/utils.py
spell/api/workflows_client.py
spell/api/workspaces_client.py
spell/cli/__init__.py
spell/cli/__main__.py
spell/cli/adapters.py
spell/cli/api_constants.py
spell/cli/constants.py
spell/cli/exceptions.py
spell/cli/log.py
spell/cli/main.py
spell/cli/commands/__init__.py
spell/cli/commands/access_tokens.py
spell/cli/commands/archive.py
spell/cli/commands/cluster.py
spell/cli/commands/cluster_aws.py
spell/cli/commands/cluster_azure.py
spell/cli/commands/cluster_gcp.py
spell/cli/commands/cluster_private.py
spell/cli/commands/cp.py
spell/cli/commands/curl.py
spell/cli/commands/feedback.py
spell/cli/commands/hyper.py
spell/cli/commands/info.py
spell/cli/commands/jupyter.py
spell/cli/commands/keys.py
spell/cli/commands/kill.py
spell/cli/commands/kube_cluster.py
spell/cli/commands/label.py
spell/cli/commands/link.py
spell/cli/commands/login.py
spell/cli/commands/logout.py
spell/cli/commands/logs.py
spell/cli/commands/ls.py
spell/cli/commands/machine_type.py
spell/cli/commands/me.py
spell/cli/commands/model.py
spell/cli/commands/owner.py
spell/cli/commands/passwd.py
spell/cli/commands/project.py
spell/cli/commands/ps.py
spell/cli/commands/repos.py
spell/cli/commands/rm.py
spell/cli/commands/run.py
spell/cli/commands/server.py
spell/cli/commands/stats.py
spell-0.48.9.dist-info/METADATA
spell-0.48.9.dist-info/WHEEL
spell-0.48.9.dist-info/entry_points.txt
spell-0.48.9.dist-info/top_level.txt
spell-0.48.9.dist-info/RECORD
